chainlink/__init__.py
chainlink/main.py
chainlink/utils.py
chainlink/cleaning/__init__.py
chainlink/cleaning/cleaning_functions.py
chainlink/cleaning/patterns.py
chainlink/cleaning/usps_suffixes.py
chainlink/link/__init__.py
chainlink/link/link_generic.py
chainlink/link/link_utils.py
chainlink/link/tfidf_utils.py
chainlink/load/__init__.py
chainlink/load/load_generic.py
chainlink/load/load_utils.py
mi_chainlink-0.0.9.dist-info/licenses/LICENSE
mi_chainlink-0.0.9.dist-info/METADATA
mi_chainlink-0.0.9.dist-info/WHEEL
mi_chainlink-0.0.9.dist-info/entry_points.txt
mi_chainlink-0.0.9.dist-info/top_level.txt
mi_chainlink-0.0.9.dist-info/RECORD
