Metadata-Version: 2.4
Name: mi-chainlink
Version: 0.0.9
Summary: A flexible record linkage framework that enables matching between multiple datasets using both exact and fuzzy matching techniques.
Author-email: "Mansueto Institute,Austin Steinhart" <asteinhart3@gmail.com>
Project-URL: Homepage, https://mansueto-institute.github.io/mi-chainlink/
Project-URL: Repository, https://github.com/mansueto-institute/mi-chainlink
Project-URL: Documentation, https://mansueto-institute.github.io/mi-chainlink/
Keywords: python
Classifier: Intended Audience :: Developers
Classifier: Programming Language :: Python
Classifier: Programming Language :: Python :: 3
Classifier: Programming Language :: Python :: 3.10
Classifier: Programming Language :: Python :: 3.11
Classifier: Programming Language :: Python :: 3.12
Classifier: Programming Language :: Python :: 3.13
Classifier: Topic :: Software Development :: Libraries :: Python Modules
Requires-Python: <4.0,>=3.10
License-File: LICENSE
Requires-Dist: duckdb>=1.2.0
Requires-Dist: jsonschema>=4.23.0
Requires-Dist: numpy>=2.0.2
Requires-Dist: polars>=1.22.0
Requires-Dist: pyarrow>=19.0.0
Requires-Dist: python-levenshtein>=0.26.1
Requires-Dist: pyyaml>=6.0.2
Requires-Dist: rich>=14.0.0
Requires-Dist: scikit-learn>=1.6.1
Requires-Dist: scipy>=1.15.1
Requires-Dist: sparse-dot-topn>=1.1.5
Requires-Dist: sqlalchemy-mate<=2.0.0.0
Requires-Dist: typer>=0.15.2
Requires-Dist: us>=3.2.0
Requires-Dist: usaddress==0.5.11
Requires-Dist: usaddress-scourgify>=0.6.0
Requires-Dist: uszipcode>=1.0.1
Dynamic: license-file
